aioapp_redis/__init__.py
aioapp_redis-0.0.1b1.dist-info/METADATA
aioapp_redis-0.0.1b1.dist-info/RECORD
aioapp_redis-0.0.1b1.dist-info/WHEEL
aioapp_redis-0.0.1b1.dist-info/top_level.txt
tests/__init__.py
tests/conftest.py
tests/docker-compose.yml
tests/test_redis.py
