Metadata-Version: 2.1
Name: aioapp-redis
Version: 0.0.1b1
Summary: Aioapp adapter for aioredis
Home-page: https://github.com/inplat/aioapp_redis
Author: Konstantin Stepanov
Author-email: UNKNOWN
License: Apache License 2.0
Keywords: aioapp_redis
Platform: UNKNOWN
Classifier: Development Status :: 2 - Pre-Alpha
Classifier: Intended Audience :: Developers
Classifier: License :: OSI Approved :: Apache Software License
Classifier: Natural Language :: English
Classifier: Programming Language :: Python :: 3
Classifier: Programming Language :: Python :: 3.6
Requires-Dist: aioapp (==0.0.2b3)
Requires-Dist: aioredis (==1.1.0)
